btcmarketsapi/__init__.py
btcmarketsapi/api.py
btcmarketsapi-1.2.dist-info/DESCRIPTION.rst
btcmarketsapi-1.2.dist-info/METADATA
btcmarketsapi-1.2.dist-info/RECORD
btcmarketsapi-1.2.dist-info/WHEEL
btcmarketsapi-1.2.dist-info/metadata.json
btcmarketsapi-1.2.dist-info/top_level.txt
