Metadata-Version: 2.0
Name: btcmarketsapi
Version: 1.2
Summary: Python3 Wrapper for the BTCMarkets APIs
Home-page: https://github.com/SigmaAdvancedAnalytics/btcmarketsapi
Author: Joshua Barber
Author-email: contact@jbarber.info
License: MIT
Platform: UNKNOWN
